starlighter/__init__.py
starlighter/parser.py
starlighter/themes.py
starlighter-0.1.5.dist-info/WHEEL
starlighter-0.1.5.dist-info/METADATA
starlighter-0.1.5.dist-info/RECORD
