Metadata-Version: 2.4
Name: starlighter
Version: 0.1.5
Summary: Ultra-fast Python syntax highlighter for FastHTML/StarHTML with Datastar support
Keywords: syntax,highlighting,fasthtml,starhtml,datastar,python
Author: firefly
Author-email: firefly <promptsiren@gmail.com>
License-Expression: Apache-2.0
Classifier: Development Status :: 5 - Production/Stable
Classifier: Intended Audience :: Developers
Classifier: Programming Language :: Python :: 3.12
Classifier: Programming Language :: Python :: 3.13
Classifier: Topic :: Software Development :: Libraries :: Python Modules
Classifier: Topic :: Text Processing :: Markup :: HTML
Requires-Python: >=3.12
Project-URL: Documentation, https://github.com/banditburai/starlighter/blob/main/README.md
Project-URL: Homepage, https://github.com/banditburai/starlighter
Project-URL: Issues, https://github.com/banditburai/starlighter/issues
Project-URL: Repository, https://github.com/banditburai/starlighter
